analysis/__init__.py
analysis/autograde_automata.py
analysis/google_sheets.py
autograde/__init__.py
autograde/autograde.py
autograde/cython_autograde.py
autograde/defs.py
ipynb_autograde/__init__.py
ipynb_autograde/main.py
ipynb_autograde-0.1.4.dist-info/LICENSE.txt
ipynb_autograde-0.1.4.dist-info/METADATA
ipynb_autograde-0.1.4.dist-info/WHEEL
ipynb_autograde-0.1.4.dist-info/top_level.txt
ipynb_autograde-0.1.4.dist-info/RECORD
